LICENSE
README.md
setup.py
tests/test_transcoder.py
unitranscode/__init__.py
unitranscode/custom_types.py
unitranscode/transcoder.py
unitranscode/utils.py
unitranscode.egg-info/PKG-INFO
unitranscode.egg-info/SOURCES.txt
unitranscode.egg-info/dependency_links.txt
unitranscode.egg-info/requires.txt
unitranscode.egg-info/top_level.txt