Metadata-Version: 2.1
Name: unitranscode
Version: 0.2.0
Summary: Universal transcoding library
Home-page: https://github.com/MatthewScholefield/unitranscode
Author: Matthew D. Scholefield
Author-email: matthew331199@gmail.com
Keywords: unitranscode
Classifier: Development Status :: 3 - Alpha
Classifier: Intended Audience :: Developers
Classifier: Programming Language :: Python :: 3
Classifier: Programming Language :: Python :: 3.8
Classifier: Programming Language :: Python :: 3.9
Classifier: Programming Language :: Python :: 3.10
License-File: LICENSE
